AUTHORS.rst
CONTRIBUTING.rst
HISTORY.rst
LICENSE
MANIFEST.in
README.rst
setup.cfg
setup.py
docs/Makefile
docs/authors.rst
docs/conf.py
docs/contributing.rst
docs/history.rst
docs/index.rst
docs/installation.rst
docs/make.bat
docs/readme.rst
docs/usage.rst
flask_template_previewer/__init__.py
flask_template_previewer/core.py
flask_template_previewer/views.py
flask_template_previewer.egg-info/PKG-INFO
flask_template_previewer.egg-info/SOURCES.txt
flask_template_previewer.egg-info/dependency_links.txt
flask_template_previewer.egg-info/not-zip-safe
flask_template_previewer.egg-info/top_level.txt
tests/__init__.py
tests/test_flask_template_previewer.py