Metadata-Version: 1.2
Name: flask-template-previewer
Version: 0.1.1
Summary: Registers a blueprint on the flask app which will lets the jinja2 templates be previewed using their relative path in templates folder as the url, with the variables passed as url query params.
Home-page: https://github.com/SuryaSankar/flask_template_previewer
Author: Surya Sankar
Author-email: suryashankar.m@gmail.com
License: MIT license
Keywords: flask_template_previewer
Platform: UNKNOWN
Classifier: Development Status :: 2 - Pre-Alpha
Classifier: Intended Audience :: Developers
Classifier: License :: OSI Approved :: MIT License
Classifier: Natural Language :: English
Classifier: Programming Language :: Python :: 3
Classifier: Programming Language :: Python :: 3.5
Classifier: Programming Language :: Python :: 3.6
Classifier: Programming Language :: Python :: 3.7
Classifier: Programming Language :: Python :: 3.8
Requires-Python: >=3.5
